sepal_ui/__init__.py
sepal_ui/conf.py
sepal_ui/aoi/__init__.py
sepal_ui/aoi/aoi_model.py
sepal_ui/aoi/aoi_tile.py
sepal_ui/aoi/aoi_view.py
sepal_ui/bin/activate_venv.py
sepal_ui/bin/entry_point.py
sepal_ui/bin/module_deploy.py
sepal_ui/bin/module_factory.py
sepal_ui/bin/module_l10n.py
sepal_ui/bin/module_theme.py
sepal_ui/bin/module_venv.py
sepal_ui/bin/sepal_ipyvuetify.py
sepal_ui/data/gaul_iso.json
sepal_ui/data/locale.parquet
sepal_ui/frontend/__init__.py
sepal_ui/frontend/resize_trigger.py
sepal_ui/frontend/styles.py
sepal_ui/frontend/css/custom.css
sepal_ui/frontend/images/dark/open-foris.png
sepal_ui/frontend/images/dark/sepal.png
sepal_ui/frontend/images/light/open-foris.png
sepal_ui/frontend/images/light/sepal.png
sepal_ui/frontend/js/fontawesome.js
sepal_ui/frontend/js/jupyter_clip.js
sepal_ui/frontend/js/jupyter_resize.js
sepal_ui/frontend/json/aoi.json
sepal_ui/frontend/json/file_icons.json
sepal_ui/frontend/json/layer.json
sepal_ui/frontend/json/layer_hover.json
sepal_ui/logger/__init__.py
sepal_ui/logger/logger.py
sepal_ui/mapping/__init__.py
sepal_ui/mapping/aoi_control.py
sepal_ui/mapping/basemaps.py
sepal_ui/mapping/bounds.py
sepal_ui/mapping/draw_control.py
sepal_ui/mapping/fullscreen_control.py
sepal_ui/mapping/inspector_control.py
sepal_ui/mapping/layer.py
sepal_ui/mapping/layer_state_control.py
sepal_ui/mapping/layers_control.py
sepal_ui/mapping/legend_control.py
sepal_ui/mapping/map_btn.py
sepal_ui/mapping/marker_cluster.py
sepal_ui/mapping/menu_control.py
sepal_ui/mapping/sepal_map.py
sepal_ui/mapping/visualization.py
sepal_ui/mapping/zoom_control.py
sepal_ui/message/__init__.py
sepal_ui/message/ar-SA/decorator.json
sepal_ui/message/ar-SA/inspector_control.json
sepal_ui/message/ar-SA/layer_control.json
sepal_ui/message/ar-SA/locale.json
sepal_ui/message/ar-SA/password_field.json
sepal_ui/message/ar-SA/utils.json
sepal_ui/message/ar-SA/v_inspector.json
sepal_ui/message/en/decorator.json
sepal_ui/message/en/inspector_control.json
sepal_ui-3.0.1.dist-info/licenses/LICENSE.txt
sepal_ui-3.0.1.dist-info/METADATA
sepal_ui-3.0.1.dist-info/WHEEL
sepal_ui-3.0.1.dist-info/entry_points.txt
sepal_ui-3.0.1.dist-info/top_level.txt
sepal_ui-3.0.1.dist-info/RECORD
