Metadata-Version: 2.4
Name: sepal-ui
Version: 3.0.1
Summary: Wrapper for ipyvuetify widgets to unify the display of voila dashboards in SEPAL platform
Author-email: Pierrick Rambaud <pierrick.rambaud49@gmail.com>
License: MIT
Project-URL: Homepage, https://github.com/12rambau/sepal_ui
Project-URL: Download, https://github.com/12rambau/sepal_ui/archive/v_${metadata:version}.tar.gz
Keywords: UI,Python,widget,sepal
Classifier: Development Status :: 5 - Production/Stable
Classifier: Intended Audience :: Developers
Classifier: Topic :: Software Development :: Build Tools
Classifier: License :: OSI Approved :: MIT License
Classifier: Programming Language :: Python :: 3.10
Classifier: Programming Language :: Python :: 3.11
Classifier: Programming Language :: Python :: 3.12
Requires-Python: >=3.10
License-File: LICENSE.txt
Requires-Dist: tomli
Requires-Dist: ipykernel
Requires-Dist: ipyvuetify
Requires-Dist: markdown
Requires-Dist: ipyleaflet>=0.14.0
Requires-Dist: earthengine-api>1.6.0
Requires-Dist: colorama
Requires-Dist: pipreqs
Requires-Dist: rioxarray
Requires-Dist: dask
Requires-Dist: geopandas>=0.14.0
Requires-Dist: matplotlib
Requires-Dist: jupyter-server-proxy
Requires-Dist: planet<3.0,>=2.0
Requires-Dist: pyarrow
Requires-Dist: localtileserver>=0.10.1
Requires-Dist: pygaul>=0.4.2
Requires-Dist: pygadm>=0.5.0
Requires-Dist: python-box
Requires-Dist: tqdm
Requires-Dist: Deprecated>=1.2.14
Requires-Dist: anyascii
Requires-Dist: natsort
Requires-Dist: typing-extensions
Requires-Dist: solara
Requires-Dist: ee-client>=2.5.0
Requires-Dist: colorlog
Requires-Dist: reactivex
Provides-Extra: dev
Requires-Dist: pre-commit>=2.18.0; extra == "dev"
Requires-Dist: commitizen; extra == "dev"
Requires-Dist: nox; extra == "dev"
Requires-Dist: tomli; extra == "dev"
Requires-Dist: jupyter; extra == "dev"
Requires-Dist: voila; extra == "dev"
Requires-Dist: mypy; extra == "dev"
Requires-Dist: colorlog; extra == "dev"
Provides-Extra: test
Requires-Dist: pytest; extra == "test"
Requires-Dist: pytest-sugar; extra == "test"
Requires-Dist: pytest-icdiff; extra == "test"
Requires-Dist: pytest-cov; extra == "test"
Requires-Dist: pytest-deadfixtures; extra == "test"
Requires-Dist: Flake8-pyproject; extra == "test"
Requires-Dist: nbmake; extra == "test"
Requires-Dist: pytest-regressions; extra == "test"
Requires-Dist: tomli; extra == "test"
Requires-Dist: colorlog; extra == "test"
Provides-Extra: doc
Requires-Dist: sphinx; extra == "doc"
Requires-Dist: jupyter-sphinx; extra == "doc"
Requires-Dist: pydata-sphinx-theme; extra == "doc"
Requires-Dist: sphinx-notfound-page; extra == "doc"
Requires-Dist: sphinx-copybutton; extra == "doc"
Requires-Dist: m2r2>=0.3.3; extra == "doc"
Requires-Dist: sphinxcontrib-autoprogram; extra == "doc"
Requires-Dist: sphinx-favicon>=1.0.1; extra == "doc"
Requires-Dist: tomli; extra == "doc"
Requires-Dist: lxml_html_clean; extra == "doc"
Dynamic: license-file
